eng/__init__.py
eng/__main__.py
eng/_cli.py
eng/_fixer.py
eng/_replacement.py
eng/words.txt
eng-0.1.2.dist-info/LICENSE
eng-0.1.2.dist-info/WHEEL
eng-0.1.2.dist-info/METADATA
eng-0.1.2.dist-info/RECORD
